fakewindowsize/__init__.py
fakewindowsize/fakewindowsize.py
fakewindowsize-0.1.dist-info/LICENSE
fakewindowsize-0.1.dist-info/METADATA
fakewindowsize-0.1.dist-info/WHEEL
fakewindowsize-0.1.dist-info/top_level.txt
fakewindowsize-0.1.dist-info/RECORD
