Metadata-Version: 2.1
Name: fakewindowsize
Version: 0.1
Summary: Python3 module to generate realistic browsers window size.
Home-page: UNKNOWN
Author: Carlos A. Planchón
License: GPL3
Keywords: fake,window,size
Platform: UNKNOWN
Classifier: Intended Audience :: Developers
Classifier: Topic :: Software Development :: Build Tools
Classifier: Programming Language :: Python :: 3.7
Requires-Dist: beautifulsoup4
Requires-Dist: requests
